{
  "pipeline": {
    "generate": {
      "cache": false
    },
    "build": {
      "outputs": [
        "dist/**",
        ".next/**"
      ],
      "dependsOn": [
        "^build",
        "^generate"
      ]
    },
    "test": {
      "outputs": [
        "coverage/**"
      ],
      "dependsOn": [
        "^build"
      ]
    },
    "lint": {
      "outputs": [],
      "dependsOn": [
        "^build"
      ]  
    },
    "dev": {
      "cache": false
    },
    "clean": {
      "cache": false
    },
    "root#build": {
      "dependsOn": [
        "^build",
        "$ANALYTICS_URL",
        "$BLOG_URL",
        "$DOCS_URL"
      ],
      "outputs": [".next/**"]
    }
  }
}
